azure/synapse/__init__.py
azure/synapse/_configuration.py
azure/synapse/_synapse_client.py
azure/synapse/_version.py
azure/synapse/py.typed
azure/synapse/accesscontrol/__init__.py
azure/synapse/accesscontrol/_access_control_client.py
azure/synapse/accesscontrol/_configuration.py
azure/synapse/accesscontrol/_version.py
azure/synapse/accesscontrol/py.typed
azure/synapse/accesscontrol/aio/__init__.py
azure/synapse/accesscontrol/aio/_access_control_client_async.py
azure/synapse/accesscontrol/aio/_configuration_async.py
azure/synapse/accesscontrol/aio/operations_async/__init__.py
azure/synapse/accesscontrol/aio/operations_async/_access_control_operations_async.py
azure/synapse/accesscontrol/models/__init__.py
azure/synapse/accesscontrol/models/_models.py
azure/synapse/accesscontrol/models/_models_py3.py
azure/synapse/accesscontrol/operations/__init__.py
azure/synapse/accesscontrol/operations/_access_control_operations.py
azure/synapse/aio/__init__.py
azure/synapse/aio/_configuration_async.py
azure/synapse/aio/_synapse_client_async.py
azure/synapse/aio/operations_async/__init__.py
azure/synapse/aio/operations_async/_monitoring_operations_async.py
azure/synapse/aio/operations_async/_spark_batch_operations_async.py
azure/synapse/aio/operations_async/_spark_session_operations_async.py
azure/synapse/aio/operations_async/_workspace_acl_operations_async.py
azure/synapse/artifacts/__init__.py
azure/synapse/artifacts/_artifacts_client.py
azure/synapse/artifacts/_configuration.py
azure/synapse/artifacts/_version.py
azure/synapse/artifacts/py.typed
azure/synapse/artifacts/aio/__init__.py
azure/synapse/artifacts/aio/_artifacts_client_async.py
azure/synapse/artifacts/aio/_configuration_async.py
azure/synapse/artifacts/aio/operations_async/__init__.py
azure/synapse/artifacts/aio/operations_async/_data_flow_debug_session_operations_async.py
azure/synapse/artifacts/aio/operations_async/_data_flow_operations_async.py
azure_synapse-0.1.2.dist-info/LICENSE.txt
azure_synapse-0.1.2.dist-info/METADATA
azure_synapse-0.1.2.dist-info/WHEEL
azure_synapse-0.1.2.dist-info/top_level.txt
azure_synapse-0.1.2.dist-info/RECORD
